cpie/__init__.py
cpie/cpie.py
cpie/ellipsoid.py
cpie/enclosure.py
cpie/helper.py
cpie/solution.py
cpie-1.0.0.dist-info/LICENSE
cpie-1.0.0.dist-info/METADATA
cpie-1.0.0.dist-info/WHEEL
cpie-1.0.0.dist-info/top_level.txt
cpie-1.0.0.dist-info/RECORD
