Metadata-Version: 2.1
Name: cpie
Version: 1.0.0
Summary: An evolutionary computation algorithm named CPIE in Python.
Home-page: https://github.com/tdj-lomf/cpie
Author: Jun Toda
Author-email: lomf@hotmail.co.jp
License: UNKNOWN
Platform: UNKNOWN
Classifier: Programming Language :: Python :: 3
Classifier: License :: OSI Approved :: MIT License
Classifier: Operating System :: OS Independent
Requires-Python: >=3.6
Requires-Dist: numpy
